peskit/__init__.py
peskit/common/__init__.py
peskit/common/constant.py
peskit/common/distribution.py
peskit/common/function.py
peskit/fit/__init__.py
peskit/fit/broadening/__init__.py
peskit/fit/broadening/function.py
peskit/fit/broadening/model.py
peskit/fit/fermi_dirac/__init__.py
peskit/fit/fermi_dirac/function.py
peskit/fit/fermi_dirac/model.py
peskit/fit/fermi_dirac/wrapper.py
peskit/fit/lorentzian/__init__.py
peskit/fit/lorentzian/function.py
peskit/fit/lorentzian/model.py
peskit/fit/model/__init__.py
peskit/fit/shirley/__init__.py
peskit/fit/shirley/wrapper.py
peskit/io/__init__.py
peskit/io/loader.py
peskit/plot/__init__.py
peskit/plot/axis.py
peskit/plot/colorbar.py
peskit/plot/figure.py
peskit/plot/label.py
peskit/plot/stylelib/phys_rev.mplstyle
peskit/sim/__init__.py
peskit/sim/cut.py
peskit/sim/edc.py
peskit-0.5.0.dist-info/METADATA
peskit-0.5.0.dist-info/WHEEL
peskit-0.5.0.dist-info/licenses/LICENSE
peskit-0.5.0.dist-info/RECORD
