Metadata-Version: 2.4
Name: peskit
Version: 0.5.0
Summary: peskit
Project-URL: Repository, https://github.com/mgjho/peskit.git
Project-URL: Issues, https://github.com/mgjho/peskit/issues
Author-email: Mingi Jho <mingi.jho@kaist.ac.kr>
License:                     GNU GENERAL PUBLIC LICENSE
License-File: LICENSE
Keywords: ARPES,Condensed Matter Physics
Classifier: Development Status :: 4 - Beta
Classifier: Intended Audience :: Science/Research
Classifier: License :: OSI Approved :: GNU General Public License v3 or later (GPLv3+)
Classifier: Operating System :: OS Independent
Classifier: Programming Language :: Python :: 3.11
Classifier: Programming Language :: Python :: 3.12
Classifier: Programming Language :: Python :: 3.13
Classifier: Topic :: Scientific/Engineering :: Physics
Requires-Python: >=3.11
Requires-Dist: igor2>=0.5.9
Requires-Dist: lmfit>=1.3.2
Requires-Dist: matplotlib>=3.10.0
Requires-Dist: numba>=0.61.0
Requires-Dist: numpy>=1.3.2
Requires-Dist: xarray>=2025.1.2
Requires-Dist: xrfit
